{
  "_class": "shapePath",
  "booleanOperation": -1,
  "do_objectID": "0C59C626-AEEF-4B1E-87E8-1D9DB099D8C9",
  "edited": true,
  "exportOptions": {
    "_class": "exportOptions",
    "exportFormats": [
    ],
    "includedLayerIds": [
    ],
    "layerOptions": 0,
    "shouldTrim": false
  },
  "frame": {
    "_class": "rect",
    "constrainProportions": false,
    "height": 13.47470503597122,
    "width": 3.937208633093526,
    "x": 0,
    "y": 0
  },
  "isFlippedHorizontal": false,
  "isFlippedVertical": false,
  "isLocked": false,
  "isVisible": true,
  "layerListExpandedType": 0,
  "name": "Path",
  "nameIsFixed": false,
  "path": {
    "_class": "path",
    "isClosed": false,
    "pointRadiusBehaviour": 0,
    "points": [
      {
        "_class": "curvePoint",
        "cornerRadius": 0,
        "curveFrom": "{0.2246195676007543, 0}",
        "curveMode": 4,
        "curveTo": "{0.50002192693943792, 0}",
        "hasCurveFrom": true,
        "hasCurveTo": false,
        "point": "{0.50002192693943792, 0}"
      },
      {
        "_class": "curvePoint",
        "cornerRadius": 0,
        "curveFrom": "{0, 0.14557732473955987}",
        "curveMode": 4,
        "curveTo": "{0, 0.065465588600863767}",
        "hasCurveFrom": false,
        "hasCurveTo": true,
        "point": "{0, 0.14557732473955987}"
      },
      {
        "_class": "curvePoint",
        "cornerRadius": 0,
        "curveFrom": "{0, 0.93464973539549734}",
        "curveMode": 4,
        "curveTo": "{0, 0.85373073128227484}",
        "hasCurveFrom": true,
        "hasCurveTo": false,
        "point": "{0, 0.85373073128227484}"
      },
      {
        "_class": "curvePoint",
        "cornerRadius": 0,
        "curveFrom": "{0.77481033197386351, 1}",
        "curveMode": 2,
        "curveTo": "{0.2246195676007543, 1}",
        "hasCurveFrom": true,
        "hasCurveTo": true,
        "point": "{0.50002192693943792, 1}"
      },
      {
        "_class": "curvePoint",
        "cornerRadius": 0,
        "curveFrom": "{1, 0.85373073128227484}",
        "curveMode": 4,
        "curveTo": "{1, 0.93464973539549734}",
        "hasCurveFrom": false,
        "hasCurveTo": true,
        "point": "{1, 0.85373073128227484}"
      },
      {
        "_class": "curvePoint",
        "cornerRadius": 0,
        "curveFrom": "{1, 0.065465588600863767}",
        "curveMode": 4,
        "curveTo": "{1, 0.14557732473955987}",
        "hasCurveFrom": true,
        "hasCurveTo": false,
        "point": "{1, 0.14557732473955987}"
      },
      {
        "_class": "curvePoint",
        "cornerRadius": 0,
        "curveFrom": "{0.50002192693943792, 0}",
        "curveMode": 4,
        "curveTo": "{0.77481033197386351, 0}",
        "hasCurveFrom": false,
        "hasCurveTo": true,
        "point": "{0.50002192693943792, 0}"
      }
    ]
  },
  "resizingConstraint": 63,
  "resizingType": 0,
  "rotation": 0,
  "shouldBreakMaskChain": false
}