{
  "_class": "shapePath",
  "booleanOperation": -1,
  "do_objectID": "02810E8F-BAEC-41DD-813F-1A8B4B529742",
  "edited": true,
  "exportOptions": {
    "_class": "exportOptions",
    "exportFormats": [
    ],
    "includedLayerIds": [
    ],
    "layerOptions": 0,
    "shouldTrim": false
  },
  "frame": {
    "_class": "rect",
    "constrainProportions": false,
    "height": 11.46106046511628,
    "width": 2.631962790697656,
    "x": 177.1517023255814,
    "y": 18.68338604651163
  },
  "isFlippedHorizontal": false,
  "isFlippedVertical": false,
  "isLocked": false,
  "isVisible": true,
  "layerListExpandedType": 0,
  "name": "Path",
  "nameIsFixed": false,
  "path": {
    "_class": "path",
    "isClosed": true,
    "pointRadiusBehaviour": 0,
    "points": [
      {
        "_class": "curvePoint",
        "cornerRadius": 0,
        "curveFrom": "{0, 1}",
        "curveMode": 1,
        "curveTo": "{0, 1}",
        "hasCurveFrom": false,
        "hasCurveTo": false,
        "point": "{0, 1}"
      },
      {
        "_class": "curvePoint",
        "cornerRadius": 0,
        "curveFrom": "{1, 1}",
        "curveMode": 1,
        "curveTo": "{1, 1}",
        "hasCurveFrom": false,
        "hasCurveTo": false,
        "point": "{1, 1}"
      },
      {
        "_class": "curvePoint",
        "cornerRadius": 0,
        "curveFrom": "{1, 0}",
        "curveMode": 1,
        "curveTo": "{1, 0}",
        "hasCurveFrom": false,
        "hasCurveTo": false,
        "point": "{1, 0}"
      },
      {
        "_class": "curvePoint",
        "cornerRadius": 0,
        "curveFrom": "{0, 0}",
        "curveMode": 1,
        "curveTo": "{0, 0}",
        "hasCurveFrom": false,
        "hasCurveTo": false,
        "point": "{0, 0}"
      }
    ]
  },
  "resizingConstraint": 63,
  "resizingType": 0,
  "rotation": 0,
  "shouldBreakMaskChain": false
}